encrypt_tools/__init__.py
encrypt_tools/encrypt_aes.py
encrypt_tools/encrypt_files.py
encrypt_tools/encrypt_rsa.py
encrypt_tools/key_pairs.py
encrypt_tools-0.0.2.dist-info/LICENSE
encrypt_tools-0.0.2.dist-info/METADATA
encrypt_tools-0.0.2.dist-info/WHEEL
encrypt_tools-0.0.2.dist-info/top_level.txt
encrypt_tools-0.0.2.dist-info/RECORD
