Metadata-Version: 2.1
Name: encrypt-tools
Version: 0.0.2
Summary: encrypt_tools
Home-page: https://github.com/jonaqp/encrypt_tools/
Author: Jonathan Quiza
Author-email: jony327@gmail.com
License: UNKNOWN
Download-URL: https://github.com/jonaqp/encrypt_tools/archive/main.zip
Keywords: color,text,terminal
Platform: UNKNOWN
Classifier: Development Status :: 5 - Production/Stable
Classifier: Intended Audience :: Developers
Classifier: Intended Audience :: Science/Research
Classifier: Topic :: Scientific/Engineering :: Artificial Intelligence
Classifier: License :: OSI Approved :: Apache Software License
Classifier: Programming Language :: Python :: 3.8
Classifier: Programming Language :: Python :: 3.7
Requires-Dist: pycryptodome (>=3.10.1)
